{
  "local": {
    "GTM_ID": "",
    "HUBSPOT_ID": "",
    "BASE_API_URL": "http://sva.talana.com:8000/",
    "BASE_URL": "http://sva.talana.com:8000/"
  },

  "testing": {
    "GTM_ID": "",
    "HUBSPOT_ID": "",
    "BASE_API_URL": "http://sva.talana.com:8000/",
    "BASE_URL": "https://hopper.alegra.com/",
    "BASE_API_CONFIG_URL": "http://sva.talana.com:8000/"
  },

  "production": {
    "GTM_ID": "",
    "HUBSPOT_ID": "",
    "BASE_API_URL": "http://sva.talana.com:8000/",
    "BASE_URL": "http://sva.talana.com:8000/"
  }
}
